{
    "name": "epic:medium_plains_rooms",
    "fallback": "minecraft:empty",
    "elements": [
        {
            "element": {
                "element_type": "minecraft:single_pool_element",
                "projection": "rigid",
                "processors": "minecraft:mossify_20_percent",
                "location": "epic:epic_dungeon/plains_dungeon/medium_plains_rooms/medium_plains_room1"
            },
            "weight": 5
        },
        {
            "element": {
                "element_type": "minecraft:single_pool_element",
                "projection": "rigid",
                "processors": "minecraft:mossify_20_percent",
                "location": "epic:epic_dungeon/plains_dungeon/medium_plains_rooms/medium_plains_room2"
            },
            "weight": 4
        },
        {
            "element": {
                "element_type": "minecraft:single_pool_element",
                "projection": "rigid",
                "processors": "minecraft:mossify_20_percent",
                "location": "epic:epic_dungeon/plains_dungeon/medium_plains_rooms/medium_plains_room3"
            },
            "weight": 5
        },
        {
            "element": {
                "element_type": "minecraft:single_pool_element",
                "projection": "rigid",
                "processors": "minecraft:mossify_20_percent",
                "location": "epic:epic_dungeon/plains_dungeon/medium_plains_rooms/medium_plains_room4"
            },
            "weight": 5
        },
        {
            "element": {
                "element_type": "minecraft:single_pool_element",
                "projection": "rigid",
                "processors": "minecraft:mossify_20_percent",
                "location": "epic:epic_dungeon/plains_dungeon/medium_plains_rooms/medium_plains_room5"
            },
            "weight": 5
        },
        {
            "element": {
                "element_type": "minecraft:single_pool_element",
                "projection": "rigid",
                "processors": "minecraft:mossify_20_percent",
                "location": "epic:epic_dungeon/plains_dungeon/medium_plains_rooms/medium_plains_room6"
            },
            "weight": 3
        },
        {
            "element": {
                "element_type": "minecraft:single_pool_element",
                "projection": "rigid",
                "processors": "minecraft:mossify_20_percent",
                "location": "epic:epic_dungeon/plains_dungeon/medium_plains_rooms/medium_plains_room7"
            },
            "weight": 5
        },
        {
            "element": {
                "element_type": "minecraft:single_pool_element",
                "projection": "rigid",
                "processors": "minecraft:mossify_20_percent",
                "location": "epic:epic_dungeon/plains_dungeon/medium_plains_rooms/medium_plains_room8"
            },
            "weight": 5
        },
        {
            "element": {
                "element_type": "minecraft:single_pool_element",
                "projection": "rigid",
                "processors": "minecraft:mossify_20_percent",
                "location": "epic:epic_dungeon/plains_dungeon/medium_plains_rooms/medium_plains_room9"
            },
            "weight": 5
        },
        {
            "element": {
                "element_type": "minecraft:single_pool_element",
                "projection": "rigid",
                "processors": "minecraft:mossify_20_percent",
                "location": "epic:epic_dungeon/plains_dungeon/medium_plains_rooms/medium_plains_room10"
            },
            "weight": 5
        },
        {
            "element": {
                "element_type": "minecraft:single_pool_element",
                "projection": "rigid",
                "processors": "minecraft:mossify_20_percent",
                "location": "epic:epic_dungeon/plains_dungeon/medium_plains_rooms/medium_plains_room11"
            },
            "weight": 5
        },
        {
            "element": {
                "element_type": "minecraft:single_pool_element",
                "projection": "rigid",
                "processors": "minecraft:mossify_20_percent",
                "location": "epic:epic_dungeon/plains_dungeon/medium_plains_rooms/medium_plains_room12"
            },
            "weight": 5
        },
        {
            "element": {
                "element_type": "minecraft:single_pool_element",
                "projection": "rigid",
                "processors": "minecraft:mossify_20_percent",
                "location": "epic:epic_dungeon/plains_dungeon/medium_plains_rooms/medium_plains_room13"
            },
            "weight": 5
        },
        {
            "element": {
                "element_type": "minecraft:single_pool_element",
                "projection": "rigid",
                "processors": "minecraft:mossify_20_percent",
                "location": "epic:epic_dungeon/plains_dungeon/medium_plains_rooms/medium_plains_room14"
            },
            "weight": 5
        }
    ]
}
